{
	"name": "ingestion",
	"properties": {
		"activities": [
			{
				"name": "get_schema",
				"type": "Lookup",
				"dependsOn": [],
				"policy": {
					"timeout": "0.12:00:00",
					"retry": 0,
					"retryIntervalInSeconds": 30,
					"secureOutput": false,
					"secureInput": false
				},
				"userProperties": [],
				"typeProperties": {
					"source": {
						"type": "AzureSqlSource",
						"sqlReaderQuery": "SELECT *\nFROM INFORMATION_SCHEMA.TABLES",
						"queryTimeout": "02:00:00",
						"partitionOption": "None"
					},
					"dataset": {
						"referenceName": "ds_sql_db_01",
						"type": "DatasetReference",
						"parameters": {
							"schema": "\"\"",
							"tbname": "\"\""
						}
					},
					"firstRowOnly": false
				}
			},
			{
				"name": "ingestion",
				"type": "ForEach",
				"dependsOn": [
					{
						"activity": "get_schema",
						"dependencyConditions": [
							"Succeeded"
						]
					}
				],
				"userProperties": [],
				"typeProperties": {
					"items": {
						"value": "@activity('get_schema').output.value",
						"type": "Expression"
					},
					"isSequential": false,
					"batchCount": 5,
					"activities": [
						{
							"name": "copy_tables",
							"type": "Copy",
							"dependsOn": [],
							"policy": {
								"timeout": "0.12:00:00",
								"retry": 0,
								"retryIntervalInSeconds": 30,
								"secureOutput": false,
								"secureInput": false
							},
							"userProperties": [],
							"typeProperties": {
								"source": {
									"type": "AzureSqlSource",
									"queryTimeout": "02:00:00",
									"partitionOption": "None"
								},
								"sink": {
									"type": "ParquetSink",
									"storeSettings": {
										"type": "AzureBlobFSWriteSettings"
									},
									"formatSettings": {
										"type": "ParquetWriteSettings"
									}
								},
								"enableStaging": false,
								"translator": {
									"type": "TabularTranslator",
									"typeConversion": true,
									"typeConversionSettings": {
										"allowDataTruncation": true,
										"treatBooleanAsNumber": false
									}
								}
							},
							"inputs": [
								{
									"referenceName": "ds_sql_db_01",
									"type": "DatasetReference",
									"parameters": {
										"schema": {
											"value": "@item().TABLE_SCHEMA",
											"type": "Expression"
										},
										"tbname": {
											"value": "@item().TABLE_NAME",
											"type": "Expression"
										}
									}
								}
							],
							"outputs": [
								{
									"referenceName": "ds_adls_learning",
									"type": "DatasetReference",
									"parameters": {
										"container": "bronze",
										"path": {
											"value": "@item().TABLE_SCHEMA",
											"type": "Expression"
										},
										"fileName": {
											"value": "@concat(item().TABLE_NAME,'.parquet')",
											"type": "Expression"
										}
									}
								}
							]
						}
					]
				}
			}
		],
		"annotations": []
	}
}